cvx/finance/Finance.py
cvx/finance/__init__.py
cvx/finance/cvxRegression.py
cvx/finance/util.py
cvxfin-0.3.2.dist-info/METADATA
cvxfin-0.3.2.dist-info/WHEEL
cvxfin-0.3.2.dist-info/licenses/LICENSE
cvxfin-0.3.2.dist-info/RECORD
