Metadata-Version: 2.4
Name: cvxFin
Version: 0.3.2
Summary: Good old faithful portfolio construction
Project-URL: repository, https://github.com/tschm/cvxFin
Project-URL: homepage, https://tschm.github.io/cvxFin
Author-email: Thomas Schmelzer <thomas.schmelzer@gmail.com>
License:                                  Apache License
License-File: LICENSE
Requires-Python: >=3.10
Requires-Dist: clarabel>=0.9.0
Requires-Dist: cvxpy-base>=1.6.0
Requires-Dist: numpy>=2.2.0
Requires-Dist: scikit-learn>=1.6.0
